MANIFEST.in
README.md
config.py
run.py
setup.py
HomeLab.egg-info/PKG-INFO
HomeLab.egg-info/SOURCES.txt
HomeLab.egg-info/dependency_links.txt
HomeLab.egg-info/not-zip-safe
HomeLab.egg-info/requires.txt
HomeLab.egg-info/top_level.txt
homelab/__init__.py
homelab/homelab
homelab/analysis/devicelibrary.py
homelab/analysis/ipthreatdatabase.py
homelab/analysis/networkscanner.py
homelab/analysis/nmap.py
homelab/analysis/trafficanalyzer.py
homelab/control/config.py
homelab/control/jobscheduler.py
homelab/control/utils.py
homelab/static/__init__.py
homelab/static/asset-manifest.json
homelab/static/favicon.ico
homelab/static/index.html
homelab/static/manifest.json
homelab/static/precache-manifest.dfb81671e1decf1bf6943f1a31169f8f.js
homelab/static/service-worker.js
homelab/static/world-110m.json
homelab/static/static/css/main.c673642b.chunk.css
homelab/static/static/css/main.c673642b.chunk.css.map
homelab/static/static/js/2.f8a14127.chunk.js
homelab/static/static/js/2.f8a14127.chunk.js.map
homelab/static/static/js/main.c3695aca.chunk.js
homelab/static/static/js/main.c3695aca.chunk.js.map
homelab/static/static/js/runtime~main.a8a9905a.js
homelab/static/static/js/runtime~main.a8a9905a.js.map
homelab/test/testwebsocket.py
homelab/webserver/__init__.py
homelab/webserver/webserver.py
homelab/websocket/__init__.py
homelab/websocket/websocketserver.py