Metadata-Version: 2.1
Name: HomeLab
Version: 0.1.36
Summary: Smart Home Security Platform
Home-page: http://pypi.python.org/pypi/HomeLab/
Author: Nils Wenzler
Author-email: nils.wenzler@crowgames.de
License: GPL-v3.0
Platform: UNKNOWN
